gab.py
gab-0.0.1.dist-info/LICENSE
gab-0.0.1.dist-info/METADATA
gab-0.0.1.dist-info/WHEEL
gab-0.0.1.dist-info/top_level.txt
gab-0.0.1.dist-info/RECORD
