Metadata-Version: 2.1
Name: gab
Version: 0.0.1
Summary: Python client library for the Gab.com API
Home-page: https://github.com/a-tal/gab
Author: Adam Talsma
Author-email: adam@talsma.ca
License: MIT
Download-URL: https://github.com/a-tal/gab
Platform: UNKNOWN
Classifier: Development Status :: 4 - Beta
Classifier: License :: OSI Approved :: MIT License
Classifier: Operating System :: POSIX :: Linux
Classifier: Programming Language :: Python :: 3.6
Classifier: Programming Language :: Python :: 3.7
Requires-Dist: requests (>=2.19.1)
Requires-Dist: beautifulsoup4 (>=4.6.3)
Requires-Dist: dataclasses (>=0.6); python_version < '3.7'
